{
  "pageNumber": 141,
  "manzils": [
    2
  ],
  "juzs": [
    7
  ],
  "hizbs": [
    14
  ],
  "rubElHizbs": [
    56
  ],
  "rukus": [
    114
  ],
  "chapterAndAyahRange": [
    {
      "chapterNumber": 6,
      "verseFrom": 102,
      "verseTo": 109
    }
  ],
  "ayahs": [
    {
      "chapterNumber": 6,
      "verseNumber": 102,
      "verseKey": "6:102",
      "pageNumber": 141,
      "isManzil": false,
      "manzilNumber": 2,
      "isJuz": false,
      "juzNumber": 7,
      "isHizb": false,
      "hizbNumber": 14,
      "isRubElHizb": false,
      "rubElHizbNumber": 56,
      "isRuku": false,
      "rukuNumber": 114,
      "isSajdah": false,
      "sajdahNumber": null,
      "textUthmani": "ذَٰلِكُمُ ٱللَّهُ رَبُّكُمْ ۖ لَآ إِلَـٰهَ إِلَّا هُوَ ۖ خَـٰلِقُ كُلِّ شَىْءٍ فَٱعْبُدُوهُ ۚ وَهُوَ عَلَىٰ كُلِّ شَىْءٍ وَكِيلٌ",
      "wordByWord": "ذَٰلِكُمُ [That] ٱللَّهُ [(is) Allah] رَبُّكُمْ ۖ [your Lord] لَآ [(there is) no] إِلَـٰهَ [god] إِلَّا [except] هُوَ ۖ [Him] خَـٰلِقُ [(the) Creator] كُلِّ [(of) every] شَىْءٍۢ [thing] فَٱعْبُدُوهُ ۚ [so worship Him] وَهُوَ [And He] عَلَىٰ [(is) on] كُلِّ [every] شَىْءٍۢ [thing] وَكِيلٌۭ [a Guardian]",
      "transliteration": "Thalikumu Allahu rabbukum lailaha illa huwa khaliqu kulli shay-in faAAbudoohuwahuwa AAala kulli shay-in wakeel",
      "reciterTimestamps": {
        "Mishari Rashid al-`Afasy": {
          "timestampFrom": 2512190,
          "timestampTo": 2533060
        },
        "Shaykh Samir al-Nass": {
          "timestampFrom": 2400,
          "timestampTo": 0
        }
      },
      "words": [
        {
          "chapterNumber": 6,
          "verseNumber": 102,
          "pageNumber": 141,
          "lineNumber": 1,
          "wordNumber": 1,
          "location": "6:102:1",
          "audioUrl": "wbw/006_102_001.mp3",
          "charTypeName": "word",
          "codeV1": "ﭑ",
          "qpcUthmaniHafs": "ذَٰلِكُمُ",
          "textUthmani": "ذَٰلِكُمُ",
          "translation": "That",
          "transliteration": "dhālikumu"
        },
        {
          "chapterNumber": 6,
          "verseNumber": 102,
          "pageNumber": 141,
          "lineNumber": 1,
          "wordNumber": 2,
          "location": "6:102:2",
          "audioUrl": "wbw/006_102_002.mp3",
          "charTypeName": "word",
          "codeV1": "ﭒ",
          "qpcUthmaniHafs": "ٱللَّهُ",
          "textUthmani": "ٱللَّهُ",
          "translation": "(is) Allah",
          "transliteration": "l-lahu"
        },
        {
          "chapterNumber": 6,
          "verseNumber": 102,
          "pageNumber": 141,
          "lineNumber": 1,
          "wordNumber": 3,
          "location": "6:102:3",
          "audioUrl": "wbw/006_102_003.mp3",
          "charTypeName": "word",
          "codeV1": "ﭓﭔ",
          "qpcUthmaniHafs": "رَبُّكُمۡۖ",
          "textUthmani": "رَبُّكُمْ ۖ",
          "translation": "your Lord",
          "transliteration": "rabbukum"
        },
        {
          "chapterNumber": 6,
          "verseNumber": 102,
          "pageNumber": 141,
          "lineNumber": 1,
          "wordNumber": 4,
          "location": "6:102:4",
          "audioUrl": "wbw/006_102_005.mp3",
          "charTypeName": "word",
          "codeV1": "ﭕ",
          "qpcUthmaniHafs": "لَآ",
          "textUthmani": "لَآ",
          "translation": "(there is) no",
          "transliteration": "lā"
        },
        {
          "chapterNumber": 6,
          "verseNumber": 102,
          "pageNumber": 141,
          "lineNumber": 1,
          "wordNumber": 5,
          "location": "6:102:5",
          "audioUrl": "wbw/006_102_006.mp3",
          "charTypeName": "word",
          "codeV1": "ﭖ",
          "qpcUthmaniHafs": "إِلَٰهَ",
          "textUthmani": "إِلَـٰهَ",
          "translation": "god",
          "transliteration": "ilāha"
        },
        {
          "chapterNumber": 6,
          "verseNumber": 102,
          "pageNumber": 141,
          "lineNumber": 1,
          "wordNumber": 6,
          "location": "6:102:6",
          "audioUrl": "wbw/006_102_007.mp3",
          "charTypeName": "word",
          "codeV1": "ﭗ",
          "qpcUthmaniHafs": "إِلَّا",
          "textUthmani": "إِلَّا",
          "translation": "except",
          "transliteration": "illā"
        },
        {
          "chapterNumber": 6,
          "verseNumber": 102,
          "pageNumber": 141,
          "lineNumber": 1,
          "wordNumber": 7,
          "location": "6:102:7",
          "audioUrl": "wbw/006_102_008.mp3",
          "charTypeName": "word",
          "codeV1": "ﭘﭙ",
          "qpcUthmaniHafs": "هُوَۖ",
          "textUthmani": "هُوَ ۖ",
          "translation": "Him",
          "transliteration": "huwa"
        },
        {
          "chapterNumber": 6,
          "verseNumber": 102,
          "pageNumber": 141,
          "lineNumber": 1,
          "wordNumber": 8,
          "location": "6:102:8",
          "audioUrl": "wbw/006_102_010.mp3",
          "charTypeName": "word",
          "codeV1": "ﭚ",
          "qpcUthmaniHafs": "خَٰلِقُ",
          "textUthmani": "خَـٰلِقُ",
          "translation": "(the) Creator",
          "transliteration": "khāliqu"
        },
        {
          "chapterNumber": 6,
          "verseNumber": 102,
          "pageNumber": 141,
          "lineNumber": 1,
          "wordNumber": 9,
          "location": "6:102:9",
          "audioUrl": "wbw/006_102_011.mp3",
          "charTypeName": "word",
          "codeV1": "ﭛ",
          "qpcUthmaniHafs": "كُلِّ",
          "textUthmani": "كُلِّ",
          "translation": "(of) every",
          "transliteration": "kulli"
        },
        {
          "chapterNumber": 6,
          "verseNumber": 102,
          "pageNumber": 141,
          "lineNumber": 1,
          "wordNumber": 10,
          "location": "6:102:10",
          "audioUrl": "wbw/006_102_012.mp3",
          "charTypeName": "word",
          "codeV1": "ﭜ",
          "qpcUthmaniHafs": "شَيۡءٖ",
          "textUthmani": "شَىْءٍۢ",
          "translation": "thing",
          "transliteration": "shayin"
        },
        {
          "chapterNumber": 6,
          "verseNumber": 102,
          "pageNumber": 141,
          "lineNumber": 2,
          "wordNumber": 11,
          "location": "6:102:11",
          "audioUrl": "wbw/006_102_013.mp3",
          "charTypeName": "word",
          "codeV1": "ﭝﭞ",
          "qpcUthmaniHafs": "فَٱعۡبُدُوهُۚ",
          "textUthmani": "فَٱعْبُدُوهُ ۚ",
          "translation": "so worship Him",
          "transliteration": "fa-uʿ'budūhu"
        },
        {
          "chapterNumber": 6,
          "verseNumber": 102,
          "pageNumber": 141,
          "lineNumber": 2,
          "wordNumber": 12,
          "location": "6:102:12",
          "audioUrl": "wbw/006_102_015.mp3",
          "charTypeName": "word",
          "codeV1": "ﭟ",
          "qpcUthmaniHafs": "وَهُوَ",
          "textUthmani": "وَهُوَ",
          "translation": "And He",
          "transliteration": "wahuwa"
        },
        {
          "chapterNumber": 6,
          "verseNumber": 102,
          "pageNumber": 141,
          "lineNumber": 2,
          "wordNumber": 13,
          "location": "6:102:13",
          "audioUrl": "wbw/006_102_016.mp3",
          "charTypeName": "word",
          "codeV1": "ﭠ",
          "qpcUthmaniHafs": "عَلَىٰ",
          "textUthmani": "عَلَىٰ",
          "translation": "(is) on",
          "transliteration": "ʿalā"
        },
        {
          "chapterNumber": 6,
          "verseNumber": 102,
          "pageNumber": 141,
          "lineNumber": 2,
          "wordNumber": 14,
          "location": "6:102:14",
          "audioUrl": "wbw/006_102_017.mp3",
          "charTypeName": "word",
          "codeV1": "ﭡ",
          "qpcUthmaniHafs": "كُلِّ",
          "textUthmani": "كُلِّ",
          "translation": "every",
          "transliteration": "kulli"
        },
        {
          "chapterNumber": 6,
          "verseNumber": 102,
          "pageNumber": 141,
          "lineNumber": 2,
          "wordNumber": 15,
          "location": "6:102:15",
          "audioUrl": "wbw/006_102_018.mp3",
          "charTypeName": "word",
          "codeV1": "ﭢ",
          "qpcUthmaniHafs": "شَيۡءٖ",
          "textUthmani": "شَىْءٍۢ",
          "translation": "thing",
          "transliteration": "shayin"
        },
        {
          "chapterNumber": 6,
          "verseNumber": 102,
          "pageNumber": 141,
          "lineNumber": 2,
          "wordNumber": 16,
          "location": "6:102:16",
          "audioUrl": "wbw/006_102_019.mp3",
          "charTypeName": "word",
          "codeV1": "ﭣ",
          "qpcUthmaniHafs": "وَكِيلٞ",
          "textUthmani": "وَكِيلٌۭ",
          "translation": "a Guardian",
          "transliteration": "wakīlun"
        },
        {
          "chapterNumber": 6,
          "verseNumber": 102,
          "pageNumber": 141,
          "lineNumber": 2,
          "wordNumber": 17,
          "location": "6:102:17",
          "audioUrl": null,
          "charTypeName": "end",
          "codeV1": "ﭤ",
          "qpcUthmaniHafs": "١٠٢",
          "textUthmani": "١٠٢",
          "translation": "(102)",
          "transliteration": null
        }
      ]
    },
    {
      "chapterNumber": 6,
      "verseNumber": 103,
      "verseKey": "6:103",
      "pageNumber": 141,
      "isManzil": false,
      "manzilNumber": 2,
      "isJuz": false,
      "juzNumber": 7,
      "isHizb": false,
      "hizbNumber": 14,
      "isRubElHizb": false,
      "rubElHizbNumber": 56,
      "isRuku": false,
      "rukuNumber": 114,
      "isSajdah": false,
      "sajdahNumber": null,
      "textUthmani": "لَّا تُدْرِكُهُ ٱلْأَبْصَـٰرُ وَهُوَ يُدْرِكُ ٱلْأَبْصَـٰرَ ۖ وَهُوَ ٱللَّطِيفُ ٱلْخَبِيرُ",
      "wordByWord": "لَّا [Not (can)] تُدْرِكُهُ [grasp Him] ٱلْأَبْصَـٰرُ [the visions] وَهُوَ [but He] يُدْرِكُ [(can) grasp] ٱلْأَبْصَـٰرَ ۖ [(all) the vision] وَهُوَ [and He (is)] ٱللَّطِيفُ [the All-Subtle] ٱلْخَبِيرُ [the All-Aware]",
      "transliteration": "La tudrikuhu al-absaru wahuwayudriku al-absara wahuwa allateefu alkhabeer",
      "reciterTimestamps": {
        "Mishari Rashid al-`Afasy": {
          "timestampFrom": 2533060,
          "timestampTo": 2543560
        }
      },
      "words": [
        {
          "chapterNumber": 6,
          "verseNumber": 103,
          "pageNumber": 141,
          "lineNumber": 2,
          "wordNumber": 1,
          "location": "6:103:1",
          "audioUrl": "wbw/006_103_001.mp3",
          "charTypeName": "word",
          "codeV1": "ﭥ",
          "qpcUthmaniHafs": "لَّا",
          "textUthmani": "لَّا",
          "translation": "Not (can)",
          "transliteration": "lā"
        },
        {
          "chapterNumber": 6,
          "verseNumber": 103,
          "pageNumber": 141,
          "lineNumber": 2,
          "wordNumber": 2,
          "location": "6:103:2",
          "audioUrl": "wbw/006_103_002.mp3",
          "charTypeName": "word",
          "codeV1": "ﭦ",
          "qpcUthmaniHafs": "تُدۡرِكُهُ",
          "textUthmani": "تُدْرِكُهُ",
          "translation": "grasp Him",
          "transliteration": "tud'rikuhu"
        },
        {
          "chapterNumber": 6,
          "verseNumber": 103,
          "pageNumber": 141,
          "lineNumber": 3,
          "wordNumber": 3,
          "location": "6:103:3",
          "audioUrl": "wbw/006_103_003.mp3",
          "charTypeName": "word",
          "codeV1": "ﭧ",
          "qpcUthmaniHafs": "ٱلۡأَبۡصَٰرُ",
          "textUthmani": "ٱلْأَبْصَـٰرُ",
          "translation": "the visions",
          "transliteration": "l-abṣāru"
        },
        {
          "chapterNumber": 6,
          "verseNumber": 103,
          "pageNumber": 141,
          "lineNumber": 3,
          "wordNumber": 4,
          "location": "6:103:4",
          "audioUrl": "wbw/006_103_004.mp3",
          "charTypeName": "word",
          "codeV1": "ﭨ",
          "qpcUthmaniHafs": "وَهُوَ",
          "textUthmani": "وَهُوَ",
          "translation": "but He",
          "transliteration": "wahuwa"
        },
        {
          "chapterNumber": 6,
          "verseNumber": 103,
          "pageNumber": 141,
          "lineNumber": 3,
          "wordNumber": 5,
          "location": "6:103:5",
          "audioUrl": "wbw/006_103_005.mp3",
          "charTypeName": "word",
          "codeV1": "ﭩ",
          "qpcUthmaniHafs": "يُدۡرِكُ",
          "textUthmani": "يُدْرِكُ",
          "translation": "(can) grasp",
          "transliteration": "yud'riku"
        },
        {
          "chapterNumber": 6,
          "verseNumber": 103,
          "pageNumber": 141,
          "lineNumber": 3,
          "wordNumber": 6,
          "location": "6:103:6",
          "audioUrl": "wbw/006_103_006.mp3",
          "charTypeName": "word",
          "codeV1": "ﭪﭫ",
          "qpcUthmaniHafs": "ٱلۡأَبۡصَٰرَۖ",
          "textUthmani": "ٱلْأَبْصَـٰرَ ۖ",
          "translation": "(all) the vision",
          "transliteration": "l-abṣāra"
        },
        {
          "chapterNumber": 6,
          "verseNumber": 103,
          "pageNumber": 141,
          "lineNumber": 3,
          "wordNumber": 7,
          "location": "6:103:7",
          "audioUrl": "wbw/006_103_008.mp3",
          "charTypeName": "word",
          "codeV1": "ﭬ",
          "qpcUthmaniHafs": "وَهُوَ",
          "textUthmani": "وَهُوَ",
          "translation": "and He (is)",
          "transliteration": "wahuwa"
        },
        {
          "chapterNumber": 6,
          "verseNumber": 103,
          "pageNumber": 141,
          "lineNumber": 3,
          "wordNumber": 8,
          "location": "6:103:8",
          "audioUrl": "wbw/006_103_009.mp3",
          "charTypeName": "word",
          "codeV1": "ﭭ",
          "qpcUthmaniHafs": "ٱللَّطِيفُ",
          "textUthmani": "ٱللَّطِيفُ",
          "translation": "the All-Subtle",
          "transliteration": "l-laṭīfu"
        },
        {
          "chapterNumber": 6,
          "verseNumber": 103,
          "pageNumber": 141,
          "lineNumber": 3,
          "wordNumber": 9,
          "location": "6:103:9",
          "audioUrl": "wbw/006_103_010.mp3",
          "charTypeName": "word",
          "codeV1": "ﭮ",
          "qpcUthmaniHafs": "ٱلۡخَبِيرُ",
          "textUthmani": "ٱلْخَبِيرُ",
          "translation": "the All-Aware",
          "transliteration": "l-khabīru"
        },
        {
          "chapterNumber": 6,
          "verseNumber": 103,
          "pageNumber": 141,
          "lineNumber": 3,
          "wordNumber": 10,
          "location": "6:103:10",
          "audioUrl": null,
          "charTypeName": "end",
          "codeV1": "ﭯ",
          "qpcUthmaniHafs": "١٠٣",
          "textUthmani": "١٠٣",
          "translation": "(103)",
          "transliteration": null
        }
      ]
    },
    {
      "chapterNumber": 6,
      "verseNumber": 104,
      "verseKey": "6:104",
      "pageNumber": 141,
      "isManzil": false,
      "manzilNumber": 2,
      "isJuz": false,
      "juzNumber": 7,
      "isHizb": false,
      "hizbNumber": 14,
      "isRubElHizb": false,
      "rubElHizbNumber": 56,
      "isRuku": false,
      "rukuNumber": 114,
      "isSajdah": false,
      "sajdahNumber": null,
      "textUthmani": "قَدْ جَآءَكُم بَصَآئِرُ مِن رَّبِّكُمْ ۖ فَمَنْ أَبْصَرَ فَلِنَفْسِهِۦ ۖ وَمَنْ عَمِىَ فَعَلَيْهَا ۚ وَمَآ أَنَا۠ عَلَيْكُم بِحَفِيظٍ",
      "wordByWord": "قَدْ [Verily] جَآءَكُم [has come to you] بَصَآئِرُ [enlightenment] مِن [from] رَّبِّكُمْ ۖ [your Lord] فَمَنْ [Then whoever] أَبْصَرَ [sees] فَلِنَفْسِهِۦ ۖ [then (it is) for his soul] وَمَنْ [and whoever] عَمِىَ [(is) blind] فَعَلَيْهَا ۚ [then (it is) against himself] وَمَآ [And not] أَنَا۠ [(am) I] عَلَيْكُم [over you] بِحَفِيظٍۢ [a guardian]",
      "transliteration": "Qad jaakum basa-iru minrabbikum faman absara falinafsihi waman AAamiya faAAalayhawama ana AAalaykum bihafeeth",
      "reciterTimestamps": {
        "Mishari Rashid al-`Afasy": {
          "timestampFrom": 2543560,
          "timestampTo": 2565080
        }
      },
      "words": [
        {
          "chapterNumber": 6,
          "verseNumber": 104,
          "pageNumber": 141,
          "lineNumber": 4,
          "wordNumber": 1,
          "location": "6:104:1",
          "audioUrl": "wbw/006_104_001.mp3",
          "charTypeName": "word",
          "codeV1": "ﭰ",
          "qpcUthmaniHafs": "قَدۡ",
          "textUthmani": "قَدْ",
          "translation": "Verily",
          "transliteration": "qad"
        },
        {
          "chapterNumber": 6,
          "verseNumber": 104,
          "pageNumber": 141,
          "lineNumber": 4,
          "wordNumber": 2,
          "location": "6:104:2",
          "audioUrl": "wbw/006_104_002.mp3",
          "charTypeName": "word",
          "codeV1": "ﭱ",
          "qpcUthmaniHafs": "جَآءَكُم",
          "textUthmani": "جَآءَكُم",
          "translation": "has come to you",
          "transliteration": "jāakum"
        },
        {
          "chapterNumber": 6,
          "verseNumber": 104,
          "pageNumber": 141,
          "lineNumber": 4,
          "wordNumber": 3,
          "location": "6:104:3",
          "audioUrl": "wbw/006_104_003.mp3",
          "charTypeName": "word",
          "codeV1": "ﭲ",
          "qpcUthmaniHafs": "بَصَآئِرُ",
          "textUthmani": "بَصَآئِرُ",
          "translation": "enlightenment",
          "transliteration": "baṣāiru"
        },
        {
          "chapterNumber": 6,
          "verseNumber": 104,
          "pageNumber": 141,
          "lineNumber": 4,
          "wordNumber": 4,
          "location": "6:104:4",
          "audioUrl": "wbw/006_104_004.mp3",
          "charTypeName": "word",
          "codeV1": "ﭳ",
          "qpcUthmaniHafs": "مِن",
          "textUthmani": "مِن",
          "translation": "from",
          "transliteration": "min"
        },
        {
          "chapterNumber": 6,
          "verseNumber": 104,
          "pageNumber": 141,
          "lineNumber": 4,
          "wordNumber": 5,
          "location": "6:104:5",
          "audioUrl": "wbw/006_104_005.mp3",
          "charTypeName": "word",
          "codeV1": "ﭴﭵ",
          "qpcUthmaniHafs": "رَّبِّكُمۡۖ",
          "textUthmani": "رَّبِّكُمْ ۖ",
          "translation": "your Lord",
          "transliteration": "rabbikum"
        },
        {
          "chapterNumber": 6,
          "verseNumber": 104,
          "pageNumber": 141,
          "lineNumber": 4,
          "wordNumber": 6,
          "location": "6:104:6",
          "audioUrl": "wbw/006_104_007.mp3",
          "charTypeName": "word",
          "codeV1": "ﭶ",
          "qpcUthmaniHafs": "فَمَنۡ",
          "textUthmani": "فَمَنْ",
          "translation": "Then whoever",
          "transliteration": "faman"
        },
        {
          "chapterNumber": 6,
          "verseNumber": 104,
          "pageNumber": 141,
          "lineNumber": 4,
          "wordNumber": 7,
          "location": "6:104:7",
          "audioUrl": "wbw/006_104_008.mp3",
          "charTypeName": "word",
          "codeV1": "ﭷ",
          "qpcUthmaniHafs": "أَبۡصَرَ",
          "textUthmani": "أَبْصَرَ",
          "translation": "sees",
          "transliteration": "abṣara"
        },
        {
          "chapterNumber": 6,
          "verseNumber": 104,
          "pageNumber": 141,
          "lineNumber": 4,
          "wordNumber": 8,
          "location": "6:104:8",
          "audioUrl": "wbw/006_104_009.mp3",
          "charTypeName": "word",
          "codeV1": "ﭸﭹ",
          "qpcUthmaniHafs": "فَلِنَفۡسِهِۦۖ",
          "textUthmani": "فَلِنَفْسِهِۦ ۖ",
          "translation": "then (it is) for his soul",
          "transliteration": "falinafsihi"
        },
        {
          "chapterNumber": 6,
          "verseNumber": 104,
          "pageNumber": 141,
          "lineNumber": 4,
          "wordNumber": 9,
          "location": "6:104:9",
          "audioUrl": "wbw/006_104_011.mp3",
          "charTypeName": "word",
          "codeV1": "ﭺ",
          "qpcUthmaniHafs": "وَمَنۡ",
          "textUthmani": "وَمَنْ",
          "translation": "and whoever",
          "transliteration": "waman"
        },
        {
          "chapterNumber": 6,
          "verseNumber": 104,
          "pageNumber": 141,
          "lineNumber": 4,
          "wordNumber": 10,
          "location": "6:104:10",
          "audioUrl": "wbw/006_104_012.mp3",
          "charTypeName": "word",
          "codeV1": "ﭻ",
          "qpcUthmaniHafs": "عَمِيَ",
          "textUthmani": "عَمِىَ",
          "translation": "(is) blind",
          "transliteration": "ʿamiya"
        },
        {
          "chapterNumber": 6,
          "verseNumber": 104,
          "pageNumber": 141,
          "lineNumber": 5,
          "wordNumber": 11,
          "location": "6:104:11",
          "audioUrl": "wbw/006_104_013.mp3",
          "charTypeName": "word",
          "codeV1": "ﭼﭽ",
          "qpcUthmaniHafs": "فَعَلَيۡهَاۚ",
          "textUthmani": "فَعَلَيْهَا ۚ",
          "translation": "then (it is) against himself",
          "transliteration": "faʿalayhā"
        },
        {
          "chapterNumber": 6,
          "verseNumber": 104,
          "pageNumber": 141,
          "lineNumber": 5,
          "wordNumber": 12,
          "location": "6:104:12",
          "audioUrl": "wbw/006_104_015.mp3",
          "charTypeName": "word",
          "codeV1": "ﭾ",
          "qpcUthmaniHafs": "وَمَآ",
          "textUthmani": "وَمَآ",
          "translation": "And not",
          "transliteration": "wamā"
        },
        {
          "chapterNumber": 6,
          "verseNumber": 104,
          "pageNumber": 141,
          "lineNumber": 5,
          "wordNumber": 13,
          "location": "6:104:13",
          "audioUrl": "wbw/006_104_016.mp3",
          "charTypeName": "word",
          "codeV1": "ﭿ",
          "qpcUthmaniHafs": "أَنَا۠",
          "textUthmani": "أَنَا۠",
          "translation": "(am) I",
          "transliteration": "anā"
        },
        {
          "chapterNumber": 6,
          "verseNumber": 104,
          "pageNumber": 141,
          "lineNumber": 5,
          "wordNumber": 14,
          "location": "6:104:14",
          "audioUrl": "wbw/006_104_017.mp3",
          "charTypeName": "word",
          "codeV1": "ﮀ",
          "qpcUthmaniHafs": "عَلَيۡكُم",
          "textUthmani": "عَلَيْكُم",
          "translation": "over you",
          "transliteration": "ʿalaykum"
        },
        {
          "chapterNumber": 6,
          "verseNumber": 104,
          "pageNumber": 141,
          "lineNumber": 5,
          "wordNumber": 15,
          "location": "6:104:15",
          "audioUrl": "wbw/006_104_018.mp3",
          "charTypeName": "word",
          "codeV1": "ﮁ",
          "qpcUthmaniHafs": "بِحَفِيظٖ",
          "textUthmani": "بِحَفِيظٍۢ",
          "translation": "a guardian",
          "transliteration": "biḥafīẓin"
        },
        {
          "chapterNumber": 6,
          "verseNumber": 104,
          "pageNumber": 141,
          "lineNumber": 5,
          "wordNumber": 16,
          "location": "6:104:16",
          "audioUrl": null,
          "charTypeName": "end",
          "codeV1": "ﮂ",
          "qpcUthmaniHafs": "١٠٤",
          "textUthmani": "١٠٤",
          "translation": "(104)",
          "transliteration": null
        }
      ]
    },
    {
      "chapterNumber": 6,
      "verseNumber": 105,
      "verseKey": "6:105",
      "pageNumber": 141,
      "isManzil": false,
      "manzilNumber": 2,
      "isJuz": false,
      "juzNumber": 7,
      "isHizb": false,
      "hizbNumber": 14,
      "isRubElHizb": false,
      "rubElHizbNumber": 56,
      "isRuku": false,
      "rukuNumber": 114,
      "isSajdah": false,
      "sajdahNumber": null,
      "textUthmani": "وَكَذَٰلِكَ نُصَرِّفُ ٱلْـَٔايَـٰتِ وَلِيَقُولُوا۟ دَرَسْتَ وَلِنُبَيِّنَهُۥ لِقَوْمٍ يَعْلَمُونَ",
      "wordByWord": "وَكَذَٰلِكَ [And thus] نُصَرِّفُ [We explain] ٱلْـَٔايَـٰتِ [the Signs] وَلِيَقُولُوا۟ [that they (may) say] دَرَسْتَ [You have studied] وَلِنُبَيِّنَهُۥ [and that We (may) make it clear] لِقَوْمٍۢ [for a people] يَعْلَمُونَ [who know]",
      "transliteration": "Wakathalika nusarrifu al-ayatiwaliyaqooloo darasta walinubayyinahu liqawmin yaAAlamoon",
      "reciterTimestamps": {
        "Mishari Rashid al-`Afasy": {
          "timestampFrom": 2565080,
          "timestampTo": 2578560
        }
      },
      "words": [
        {
          "chapterNumber": 6,
          "verseNumber": 105,
          "pageNumber": 141,
          "lineNumber": 5,
          "wordNumber": 1,
          "location": "6:105:1",
          "audioUrl": "wbw/006_105_001.mp3",
          "charTypeName": "word",
          "codeV1": "ﮃ",
          "qpcUthmaniHafs": "وَكَذَٰلِكَ",
          "textUthmani": "وَكَذَٰلِكَ",
          "translation": "And thus",
          "transliteration": "wakadhālika"
        },
        {
          "chapterNumber": 6,
          "verseNumber": 105,
          "pageNumber": 141,
          "lineNumber": 5,
          "wordNumber": 2,
          "location": "6:105:2",
          "audioUrl": "wbw/006_105_002.mp3",
          "charTypeName": "word",
          "codeV1": "ﮄ",
          "qpcUthmaniHafs": "نُصَرِّفُ",
          "textUthmani": "نُصَرِّفُ",
          "translation": "We explain",
          "transliteration": "nuṣarrifu"
        },
        {
          "chapterNumber": 6,
          "verseNumber": 105,
          "pageNumber": 141,
          "lineNumber": 6,
          "wordNumber": 3,
          "location": "6:105:3",
          "audioUrl": "wbw/006_105_003.mp3",
          "charTypeName": "word",
          "codeV1": "ﮅ",
          "qpcUthmaniHafs": "ٱلۡأٓيَٰتِ",
          "textUthmani": "ٱلْـَٔايَـٰتِ",
          "translation": "the Signs",
          "transliteration": "l-āyāti"
        },
        {
          "chapterNumber": 6,
          "verseNumber": 105,
          "pageNumber": 141,
          "lineNumber": 6,
          "wordNumber": 4,
          "location": "6:105:4",
          "audioUrl": "wbw/006_105_004.mp3",
          "charTypeName": "word",
          "codeV1": "ﮆ",
          "qpcUthmaniHafs": "وَلِيَقُولُواْ",
          "textUthmani": "وَلِيَقُولُوا۟",
          "translation": "that they (may) say",
          "transliteration": "waliyaqūlū"
        },
        {
          "chapterNumber": 6,
          "verseNumber": 105,
          "pageNumber": 141,
          "lineNumber": 6,
          "wordNumber": 5,
          "location": "6:105:5",
          "audioUrl": "wbw/006_105_005.mp3",
          "charTypeName": "word",
          "codeV1": "ﮇ",
          "qpcUthmaniHafs": "دَرَسۡتَ",
          "textUthmani": "دَرَسْتَ",
          "translation": "You have studied",
          "transliteration": "darasta"
        },
        {
          "chapterNumber": 6,
          "verseNumber": 105,
          "pageNumber": 141,
          "lineNumber": 6,
          "wordNumber": 6,
          "location": "6:105:6",
          "audioUrl": "wbw/006_105_006.mp3",
          "charTypeName": "word",
          "codeV1": "ﮈ",
          "qpcUthmaniHafs": "وَلِنُبَيِّنَهُۥ",
          "textUthmani": "وَلِنُبَيِّنَهُۥ",
          "translation": "and that We (may) make it clear",
          "transliteration": "walinubayyinahu"
        },
        {
          "chapterNumber": 6,
          "verseNumber": 105,
          "pageNumber": 141,
          "lineNumber": 6,
          "wordNumber": 7,
          "location": "6:105:7",
          "audioUrl": "wbw/006_105_007.mp3",
          "charTypeName": "word",
          "codeV1": "ﮉ",
          "qpcUthmaniHafs": "لِقَوۡمٖ",
          "textUthmani": "لِقَوْمٍۢ",
          "translation": "for a people",
          "transliteration": "liqawmin"
        },
        {
          "chapterNumber": 6,
          "verseNumber": 105,
          "pageNumber": 141,
          "lineNumber": 6,
          "wordNumber": 8,
          "location": "6:105:8",
          "audioUrl": "wbw/006_105_008.mp3",
          "charTypeName": "word",
          "codeV1": "ﮊ",
          "qpcUthmaniHafs": "يَعۡلَمُونَ",
          "textUthmani": "يَعْلَمُونَ",
          "translation": "who know",
          "transliteration": "yaʿlamūna"
        },
        {
          "chapterNumber": 6,
          "verseNumber": 105,
          "pageNumber": 141,
          "lineNumber": 6,
          "wordNumber": 9,
          "location": "6:105:9",
          "audioUrl": null,
          "charTypeName": "end",
          "codeV1": "ﮋ",
          "qpcUthmaniHafs": "١٠٥",
          "textUthmani": "١٠٥",
          "translation": "(105)",
          "transliteration": null
        }
      ]
    },
    {
      "chapterNumber": 6,
      "verseNumber": 106,
      "verseKey": "6:106",
      "pageNumber": 141,
      "isManzil": false,
      "manzilNumber": 2,
      "isJuz": false,
      "juzNumber": 7,
      "isHizb": false,
      "hizbNumber": 14,
      "isRubElHizb": false,
      "rubElHizbNumber": 56,
      "isRuku": false,
      "rukuNumber": 114,
      "isSajdah": false,
      "sajdahNumber": null,
      "textUthmani": "ٱتَّبِعْ مَآ أُوحِىَ إِلَيْكَ مِن رَّبِّكَ ۖ لَآ إِلَـٰهَ إِلَّا هُوَ ۖ وَأَعْرِضْ عَنِ ٱلْمُشْرِكِينَ",
      "wordByWord": "ٱتَّبِعْ [Follow] مَآ [what] أُوحِىَ [has been inspired] إِلَيْكَ [to you] مِن [from] رَّبِّكَ ۖ [your Lord] لَآ [(there is) no] إِلَـٰهَ [god] إِلَّا [except] هُوَ ۖ [Him] وَأَعْرِضْ [and turn away] عَنِ [from] ٱلْمُشْرِكِينَ [the polytheists]",
      "transliteration": "IttabiAA ma oohiya ilayka minrabbika la ilaha illa huwa waaAAridAAani almushrikeen",
      "reciterTimestamps": {
        "Mishari Rashid al-`Afasy": {
          "timestampFrom": 2578560,
          "timestampTo": 2594290
        }
      },
      "words": [
        {
          "chapterNumber": 6,
          "verseNumber": 106,
          "pageNumber": 141,
          "lineNumber": 7,
          "wordNumber": 1,
          "location": "6:106:1",
          "audioUrl": "wbw/006_106_001.mp3",
          "charTypeName": "word",
          "codeV1": "ﮌ",
          "qpcUthmaniHafs": "ٱتَّبِعۡ",
          "textUthmani": "ٱتَّبِعْ",
          "translation": "Follow",
          "transliteration": "ittabiʿ"
        },
        {
          "chapterNumber": 6,
          "verseNumber": 106,
          "pageNumber": 141,
          "lineNumber": 7,
          "wordNumber": 2,
          "location": "6:106:2",
          "audioUrl": "wbw/006_106_002.mp3",
          "charTypeName": "word",
          "codeV1": "ﮍ",
          "qpcUthmaniHafs": "مَآ",
          "textUthmani": "مَآ",
          "translation": "what",
          "transliteration": "mā"
        },
        {
          "chapterNumber": 6,
          "verseNumber": 106,
          "pageNumber": 141,
          "lineNumber": 7,
          "wordNumber": 3,
          "location": "6:106:3",
          "audioUrl": "wbw/006_106_003.mp3",
          "charTypeName": "word",
          "codeV1": "ﮎ",
          "qpcUthmaniHafs": "أُوحِيَ",
          "textUthmani": "أُوحِىَ",
          "translation": "has been inspired",
          "transliteration": "ūḥiya"
        },
        {
          "chapterNumber": 6,
          "verseNumber": 106,
          "pageNumber": 141,
          "lineNumber": 7,
          "wordNumber": 4,
          "location": "6:106:4",
          "audioUrl": "wbw/006_106_004.mp3",
          "charTypeName": "word",
          "codeV1": "ﮏ",
          "qpcUthmaniHafs": "إِلَيۡكَ",
          "textUthmani": "إِلَيْكَ",
          "translation": "to you",
          "transliteration": "ilayka"
        },
        {
          "chapterNumber": 6,
          "verseNumber": 106,
          "pageNumber": 141,
          "lineNumber": 7,
          "wordNumber": 5,
          "location": "6:106:5",
          "audioUrl": "wbw/006_106_005.mp3",
          "charTypeName": "word",
          "codeV1": "ﮐ",
          "qpcUthmaniHafs": "مِن",
          "textUthmani": "مِن",
          "translation": "from",
          "transliteration": "min"
        },
        {
          "chapterNumber": 6,
          "verseNumber": 106,
          "pageNumber": 141,
          "lineNumber": 7,
          "wordNumber": 6,
          "location": "6:106:6",
          "audioUrl": "wbw/006_106_006.mp3",
          "charTypeName": "word",
          "codeV1": "ﮑﮒ",
          "qpcUthmaniHafs": "رَّبِّكَۖ",
          "textUthmani": "رَّبِّكَ ۖ",
          "translation": "your Lord",
          "transliteration": "rabbika"
        },
        {
          "chapterNumber": 6,
          "verseNumber": 106,
          "pageNumber": 141,
          "lineNumber": 7,
          "wordNumber": 7,
          "location": "6:106:7",
          "audioUrl": "wbw/006_106_008.mp3",
          "charTypeName": "word",
          "codeV1": "ﮓ",
          "qpcUthmaniHafs": "لَآ",
          "textUthmani": "لَآ",
          "translation": "(there is) no",
          "transliteration": "lā"
        },
        {
          "chapterNumber": 6,
          "verseNumber": 106,
          "pageNumber": 141,
          "lineNumber": 7,
          "wordNumber": 8,
          "location": "6:106:8",
          "audioUrl": "wbw/006_106_009.mp3",
          "charTypeName": "word",
          "codeV1": "ﮔ",
          "qpcUthmaniHafs": "إِلَٰهَ",
          "textUthmani": "إِلَـٰهَ",
          "translation": "god",
          "transliteration": "ilāha"
        },
        {
          "chapterNumber": 6,
          "verseNumber": 106,
          "pageNumber": 141,
          "lineNumber": 7,
          "wordNumber": 9,
          "location": "6:106:9",
          "audioUrl": "wbw/006_106_010.mp3",
          "charTypeName": "word",
          "codeV1": "ﮕ",
          "qpcUthmaniHafs": "إِلَّا",
          "textUthmani": "إِلَّا",
          "translation": "except",
          "transliteration": "illā"
        },
        {
          "chapterNumber": 6,
          "verseNumber": 106,
          "pageNumber": 141,
          "lineNumber": 7,
          "wordNumber": 10,
          "location": "6:106:10",
          "audioUrl": "wbw/006_106_011.mp3",
          "charTypeName": "word",
          "codeV1": "ﮖﮗ",
          "qpcUthmaniHafs": "هُوَۖ",
          "textUthmani": "هُوَ ۖ",
          "translation": "Him",
          "transliteration": "huwa"
        },
        {
          "chapterNumber": 6,
          "verseNumber": 106,
          "pageNumber": 141,
          "lineNumber": 7,
          "wordNumber": 11,
          "location": "6:106:11",
          "audioUrl": "wbw/006_106_013.mp3",
          "charTypeName": "word",
          "codeV1": "ﮘ",
          "qpcUthmaniHafs": "وَأَعۡرِضۡ",
          "textUthmani": "وَأَعْرِضْ",
          "translation": "and turn away",
          "transliteration": "wa-aʿriḍ"
        },
        {
          "chapterNumber": 6,
          "verseNumber": 106,
          "pageNumber": 141,
          "lineNumber": 7,
          "wordNumber": 12,
          "location": "6:106:12",
          "audioUrl": "wbw/006_106_014.mp3",
          "charTypeName": "word",
          "codeV1": "ﮙ",
          "qpcUthmaniHafs": "عَنِ",
          "textUthmani": "عَنِ",
          "translation": "from",
          "transliteration": "ʿani"
        },
        {
          "chapterNumber": 6,
          "verseNumber": 106,
          "pageNumber": 141,
          "lineNumber": 8,
          "wordNumber": 13,
          "location": "6:106:13",
          "audioUrl": "wbw/006_106_015.mp3",
          "charTypeName": "word",
          "codeV1": "ﮚ",
          "qpcUthmaniHafs": "ٱلۡمُشۡرِكِينَ",
          "textUthmani": "ٱلْمُشْرِكِينَ",
          "translation": "the polytheists",
          "transliteration": "l-mush'rikīna"
        },
        {
          "chapterNumber": 6,
          "verseNumber": 106,
          "pageNumber": 141,
          "lineNumber": 8,
          "wordNumber": 14,
          "location": "6:106:14",
          "audioUrl": null,
          "charTypeName": "end",
          "codeV1": "ﮛ",
          "qpcUthmaniHafs": "١٠٦",
          "textUthmani": "١٠٦",
          "translation": "(106)",
          "transliteration": null
        }
      ]
    },
    {
      "chapterNumber": 6,
      "verseNumber": 107,
      "verseKey": "6:107",
      "pageNumber": 141,
      "isManzil": false,
      "manzilNumber": 2,
      "isJuz": false,
      "juzNumber": 7,
      "isHizb": false,
      "hizbNumber": 14,
      "isRubElHizb": false,
      "rubElHizbNumber": 56,
      "isRuku": false,
      "rukuNumber": 114,
      "isSajdah": false,
      "sajdahNumber": null,
      "textUthmani": "وَلَوْ شَآءَ ٱللَّهُ مَآ أَشْرَكُوا۟ ۗ وَمَا جَعَلْنَـٰكَ عَلَيْهِمْ حَفِيظًا ۖ وَمَآ أَنتَ عَلَيْهِم بِوَكِيلٍ",
      "wordByWord": "وَلَوْ [And if] شَآءَ [(had) willed] ٱللَّهُ [Allah] مَآ [not (they would have)] أَشْرَكُوا۟ ۗ [associated partners (with Him)] وَمَا [And not] جَعَلْنَـٰكَ [We have made you] عَلَيْهِمْ [over them] حَفِيظًۭا ۖ [a guardian] وَمَآ [and not] أَنتَ [you] عَلَيْهِم [(are) over them] بِوَكِيلٍۢ [a manager]",
      "transliteration": "Walaw shaa Allahu maashrakoo wama jaAAalnaka AAalayhim hafeethanwama anta AAalayhim biwakeel",
      "reciterTimestamps": {
        "Mishari Rashid al-`Afasy": {
          "timestampFrom": 2594290,
          "timestampTo": 2613280
        }
      },
      "words": [
        {
          "chapterNumber": 6,
          "verseNumber": 107,
          "pageNumber": 141,
          "lineNumber": 8,
          "wordNumber": 1,
          "location": "6:107:1",
          "audioUrl": "wbw/006_107_001.mp3",
          "charTypeName": "word",
          "codeV1": "ﮜ",
          "qpcUthmaniHafs": "وَلَوۡ",
          "textUthmani": "وَلَوْ",
          "translation": "And if",
          "transliteration": "walaw"
        },
        {
          "chapterNumber": 6,
          "verseNumber": 107,
          "pageNumber": 141,
          "lineNumber": 8,
          "wordNumber": 2,
          "location": "6:107:2",
          "audioUrl": "wbw/006_107_002.mp3",
          "charTypeName": "word",
          "codeV1": "ﮝ",
          "qpcUthmaniHafs": "شَآءَ",
          "textUthmani": "شَآءَ",
          "translation": "(had) willed",
          "transliteration": "shāa"
        },
        {
          "chapterNumber": 6,
          "verseNumber": 107,
          "pageNumber": 141,
          "lineNumber": 8,
          "wordNumber": 3,
          "location": "6:107:3",
          "audioUrl": "wbw/006_107_003.mp3",
          "charTypeName": "word",
          "codeV1": "ﮞ",
          "qpcUthmaniHafs": "ٱللَّهُ",
          "textUthmani": "ٱللَّهُ",
          "translation": "Allah",
          "transliteration": "l-lahu"
        },
        {
          "chapterNumber": 6,
          "verseNumber": 107,
          "pageNumber": 141,
          "lineNumber": 8,
          "wordNumber": 4,
          "location": "6:107:4",
          "audioUrl": "wbw/006_107_004.mp3",
          "charTypeName": "word",
          "codeV1": "ﮟ",
          "qpcUthmaniHafs": "مَآ",
          "textUthmani": "مَآ",
          "translation": "not (they would have)",
          "transliteration": "mā"
        },
        {
          "chapterNumber": 6,
          "verseNumber": 107,
          "pageNumber": 141,
          "lineNumber": 8,
          "wordNumber": 5,
          "location": "6:107:5",
          "audioUrl": "wbw/006_107_005.mp3",
          "charTypeName": "word",
          "codeV1": "ﮠﮡ",
          "qpcUthmaniHafs": "أَشۡرَكُواْۗ",
          "textUthmani": "أَشْرَكُوا۟ ۗ",
          "translation": "associated partners (with Him)",
          "transliteration": "ashrakū"
        },
        {
          "chapterNumber": 6,
          "verseNumber": 107,
          "pageNumber": 141,
          "lineNumber": 8,
          "wordNumber": 6,
          "location": "6:107:6",
          "audioUrl": "wbw/006_107_007.mp3",
          "charTypeName": "word",
          "codeV1": "ﮢ",
          "qpcUthmaniHafs": "وَمَا",
          "textUthmani": "وَمَا",
          "translation": "And not",
          "transliteration": "wamā"
        },
        {
          "chapterNumber": 6,
          "verseNumber": 107,
          "pageNumber": 141,
          "lineNumber": 8,
          "wordNumber": 7,
          "location": "6:107:7",
          "audioUrl": "wbw/006_107_008.mp3",
          "charTypeName": "word",
          "codeV1": "ﮣ",
          "qpcUthmaniHafs": "جَعَلۡنَٰكَ",
          "textUthmani": "جَعَلْنَـٰكَ",
          "translation": "We have made you",
          "transliteration": "jaʿalnāka"
        },
        {
          "chapterNumber": 6,
          "verseNumber": 107,
          "pageNumber": 141,
          "lineNumber": 8,
          "wordNumber": 8,
          "location": "6:107:8",
          "audioUrl": "wbw/006_107_009.mp3",
          "charTypeName": "word",
          "codeV1": "ﮤ",
          "qpcUthmaniHafs": "عَلَيۡهِمۡ",
          "textUthmani": "عَلَيْهِمْ",
          "translation": "over them",
          "transliteration": "ʿalayhim"
        },
        {
          "chapterNumber": 6,
          "verseNumber": 107,
          "pageNumber": 141,
          "lineNumber": 9,
          "wordNumber": 9,
          "location": "6:107:9",
          "audioUrl": "wbw/006_107_010.mp3",
          "charTypeName": "word",
          "codeV1": "ﮥﮦ",
          "qpcUthmaniHafs": "حَفِيظٗاۖ",
          "textUthmani": "حَفِيظًۭا ۖ",
          "translation": "a guardian",
          "transliteration": "ḥafīẓan"
        },
        {
          "chapterNumber": 6,
          "verseNumber": 107,
          "pageNumber": 141,
          "lineNumber": 9,
          "wordNumber": 10,
          "location": "6:107:10",
          "audioUrl": "wbw/006_107_012.mp3",
          "charTypeName": "word",
          "codeV1": "ﮧ",
          "qpcUthmaniHafs": "وَمَآ",
          "textUthmani": "وَمَآ",
          "translation": "and not",
          "transliteration": "wamā"
        },
        {
          "chapterNumber": 6,
          "verseNumber": 107,
          "pageNumber": 141,
          "lineNumber": 9,
          "wordNumber": 11,
          "location": "6:107:11",
          "audioUrl": "wbw/006_107_013.mp3",
          "charTypeName": "word",
          "codeV1": "ﮨ",
          "qpcUthmaniHafs": "أَنتَ",
          "textUthmani": "أَنتَ",
          "translation": "you",
          "transliteration": "anta"
        },
        {
          "chapterNumber": 6,
          "verseNumber": 107,
          "pageNumber": 141,
          "lineNumber": 9,
          "wordNumber": 12,
          "location": "6:107:12",
          "audioUrl": "wbw/006_107_014.mp3",
          "charTypeName": "word",
          "codeV1": "ﮩ",
          "qpcUthmaniHafs": "عَلَيۡهِم",
          "textUthmani": "عَلَيْهِم",
          "translation": "(are) over them",
          "transliteration": "ʿalayhim"
        },
        {
          "chapterNumber": 6,
          "verseNumber": 107,
          "pageNumber": 141,
          "lineNumber": 9,
          "wordNumber": 13,
          "location": "6:107:13",
          "audioUrl": "wbw/006_107_015.mp3",
          "charTypeName": "word",
          "codeV1": "ﮪ",
          "qpcUthmaniHafs": "بِوَكِيلٖ",
          "textUthmani": "بِوَكِيلٍۢ",
          "translation": "a manager",
          "transliteration": "biwakīlin"
        },
        {
          "chapterNumber": 6,
          "verseNumber": 107,
          "pageNumber": 141,
          "lineNumber": 9,
          "wordNumber": 14,
          "location": "6:107:14",
          "audioUrl": null,
          "charTypeName": "end",
          "codeV1": "ﮫ",
          "qpcUthmaniHafs": "١٠٧",
          "textUthmani": "١٠٧",
          "translation": "(107)",
          "transliteration": null
        }
      ]
    },
    {
      "chapterNumber": 6,
      "verseNumber": 108,
      "verseKey": "6:108",
      "pageNumber": 141,
      "isManzil": false,
      "manzilNumber": 2,
      "isJuz": false,
      "juzNumber": 7,
      "isHizb": false,
      "hizbNumber": 14,
      "isRubElHizb": false,
      "rubElHizbNumber": 56,
      "isRuku": false,
      "rukuNumber": 114,
      "isSajdah": false,
      "sajdahNumber": null,
      "textUthmani": "وَلَا تَسُبُّوا۟ ٱلَّذِينَ يَدْعُونَ مِن دُونِ ٱللَّهِ فَيَسُبُّوا۟ ٱللَّهَ عَدْوًۢا بِغَيْرِ عِلْمٍ ۗ كَذَٰلِكَ زَيَّنَّا لِكُلِّ أُمَّةٍ عَمَلَهُمْ ثُمَّ إِلَىٰ رَبِّهِم مَّرْجِعُهُمْ فَيُنَبِّئُهُم بِمَا كَانُوا۟ يَعْمَلُونَ",
      "wordByWord": "وَلَا [And (do) not] تَسُبُّوا۟ [insult] ٱلَّذِينَ [those whom] يَدْعُونَ [they invoke] مِن [from] دُونِ [other than] ٱللَّهِ [Allah] فَيَسُبُّوا۟ [lest they insult] ٱللَّهَ [Allah] عَدْوًۢا [(in) enmity] بِغَيْرِ [without] عِلْمٍۢ ۗ [knowledge] كَذَٰلِكَ [Thus] زَيَّنَّا [We have made fair-seeming] لِكُلِّ [to every] أُمَّةٍ [community] عَمَلَهُمْ [their deed] ثُمَّ [Then] إِلَىٰ [to] رَبِّهِم [their Lord] مَّرْجِعُهُمْ [(is) their return] فَيُنَبِّئُهُم [then He will inform them] بِمَا [about what] كَانُوا۟ [they used to] يَعْمَلُونَ [do]",
      "transliteration": "Wala tasubboo allatheenayadAAoona min dooni Allahi fayasubboo AllahaAAadwan bighayri AAilmin kathalika zayyanna likulliommatin AAamalahum thumma ila rabbihim marjiAAuhumfayunabbi-ohum bima kanoo yaAAmaloon",
      "reciterTimestamps": {
        "Mishari Rashid al-`Afasy": {
          "timestampFrom": 2613280,
          "timestampTo": 2649360
        }
      },
      "words": [
        {
          "chapterNumber": 6,
          "verseNumber": 108,
          "pageNumber": 141,
          "lineNumber": 9,
          "wordNumber": 1,
          "location": "6:108:1",
          "audioUrl": "wbw/006_108_001.mp3",
          "charTypeName": "word",
          "codeV1": "ﮬ",
          "qpcUthmaniHafs": "وَلَا",
          "textUthmani": "وَلَا",
          "translation": "And (do) not",
          "transliteration": "walā"
        },
        {
          "chapterNumber": 6,
          "verseNumber": 108,
          "pageNumber": 141,
          "lineNumber": 9,
          "wordNumber": 2,
          "location": "6:108:2",
          "audioUrl": "wbw/006_108_002.mp3",
          "charTypeName": "word",
          "codeV1": "ﮭ",
          "qpcUthmaniHafs": "تَسُبُّواْ",
          "textUthmani": "تَسُبُّوا۟",
          "translation": "insult",
          "transliteration": "tasubbū"
        },
        {
          "chapterNumber": 6,
          "verseNumber": 108,
          "pageNumber": 141,
          "lineNumber": 9,
          "wordNumber": 3,
          "location": "6:108:3",
          "audioUrl": "wbw/006_108_003.mp3",
          "charTypeName": "word",
          "codeV1": "ﮮ",
          "qpcUthmaniHafs": "ٱلَّذِينَ",
          "textUthmani": "ٱلَّذِينَ",
          "translation": "those whom",
          "transliteration": "alladhīna"
        },
        {
          "chapterNumber": 6,
          "verseNumber": 108,
          "pageNumber": 141,
          "lineNumber": 10,
          "wordNumber": 4,
          "location": "6:108:4",
          "audioUrl": "wbw/006_108_004.mp3",
          "charTypeName": "word",
          "codeV1": "ﮯ",
          "qpcUthmaniHafs": "يَدۡعُونَ",
          "textUthmani": "يَدْعُونَ",
          "translation": "they invoke",
          "transliteration": "yadʿūna"
        },
        {
          "chapterNumber": 6,
          "verseNumber": 108,
          "pageNumber": 141,
          "lineNumber": 10,
          "wordNumber": 5,
          "location": "6:108:5",
          "audioUrl": "wbw/006_108_005.mp3",
          "charTypeName": "word",
          "codeV1": "ﮰ",
          "qpcUthmaniHafs": "مِن",
          "textUthmani": "مِن",
          "translation": "from",
          "transliteration": "min"
        },
        {
          "chapterNumber": 6,
          "verseNumber": 108,
          "pageNumber": 141,
          "lineNumber": 10,
          "wordNumber": 6,
          "location": "6:108:6",
          "audioUrl": "wbw/006_108_006.mp3",
          "charTypeName": "word",
          "codeV1": "ﮱ",
          "qpcUthmaniHafs": "دُونِ",
          "textUthmani": "دُونِ",
          "translation": "other than",
          "transliteration": "dūni"
        },
        {
          "chapterNumber": 6,
          "verseNumber": 108,
          "pageNumber": 141,
          "lineNumber": 10,
          "wordNumber": 7,
          "location": "6:108:7",
          "audioUrl": "wbw/006_108_007.mp3",
          "charTypeName": "word",
          "codeV1": "ﯓ",
          "qpcUthmaniHafs": "ٱللَّهِ",
          "textUthmani": "ٱللَّهِ",
          "translation": "Allah",
          "transliteration": "l-lahi"
        },
        {
          "chapterNumber": 6,
          "verseNumber": 108,
          "pageNumber": 141,
          "lineNumber": 10,
          "wordNumber": 8,
          "location": "6:108:8",
          "audioUrl": "wbw/006_108_008.mp3",
          "charTypeName": "word",
          "codeV1": "ﯔ",
          "qpcUthmaniHafs": "فَيَسُبُّواْ",
          "textUthmani": "فَيَسُبُّوا۟",
          "translation": "lest they insult",
          "transliteration": "fayasubbū"
        },
        {
          "chapterNumber": 6,
          "verseNumber": 108,
          "pageNumber": 141,
          "lineNumber": 10,
          "wordNumber": 9,
          "location": "6:108:9",
          "audioUrl": "wbw/006_108_009.mp3",
          "charTypeName": "word",
          "codeV1": "ﯕ",
          "qpcUthmaniHafs": "ٱللَّهَ",
          "textUthmani": "ٱللَّهَ",
          "translation": "Allah",
          "transliteration": "l-laha"
        },
        {
          "chapterNumber": 6,
          "verseNumber": 108,
          "pageNumber": 141,
          "lineNumber": 10,
          "wordNumber": 10,
          "location": "6:108:10",
          "audioUrl": "wbw/006_108_010.mp3",
          "charTypeName": "word",
          "codeV1": "ﯖ",
          "qpcUthmaniHafs": "عَدۡوَۢا",
          "textUthmani": "عَدْوًۢا",
          "translation": "(in) enmity",
          "transliteration": "ʿadwan"
        },
        {
          "chapterNumber": 6,
          "verseNumber": 108,
          "pageNumber": 141,
          "lineNumber": 10,
          "wordNumber": 11,
          "location": "6:108:11",
          "audioUrl": "wbw/006_108_011.mp3",
          "charTypeName": "word",
          "codeV1": "ﯗ",
          "qpcUthmaniHafs": "بِغَيۡرِ",
          "textUthmani": "بِغَيْرِ",
          "translation": "without",
          "transliteration": "bighayri"
        },
        {
          "chapterNumber": 6,
          "verseNumber": 108,
          "pageNumber": 141,
          "lineNumber": 10,
          "wordNumber": 12,
          "location": "6:108:12",
          "audioUrl": "wbw/006_108_012.mp3",
          "charTypeName": "word",
          "codeV1": "ﯘﯙ",
          "qpcUthmaniHafs": "عِلۡمٖۗ",
          "textUthmani": "عِلْمٍۢ ۗ",
          "translation": "knowledge",
          "transliteration": "ʿil'min"
        },
        {
          "chapterNumber": 6,
          "verseNumber": 108,
          "pageNumber": 141,
          "lineNumber": 10,
          "wordNumber": 13,
          "location": "6:108:13",
          "audioUrl": "wbw/006_108_014.mp3",
          "charTypeName": "word",
          "codeV1": "ﯚ",
          "qpcUthmaniHafs": "كَذَٰلِكَ",
          "textUthmani": "كَذَٰلِكَ",
          "translation": "Thus",
          "transliteration": "kadhālika"
        },
        {
          "chapterNumber": 6,
          "verseNumber": 108,
          "pageNumber": 141,
          "lineNumber": 10,
          "wordNumber": 14,
          "location": "6:108:14",
          "audioUrl": "wbw/006_108_015.mp3",
          "charTypeName": "word",
          "codeV1": "ﯛ",
          "qpcUthmaniHafs": "زَيَّنَّا",
          "textUthmani": "زَيَّنَّا",
          "translation": "We have made fair-seeming",
          "transliteration": "zayyannā"
        },
        {
          "chapterNumber": 6,
          "verseNumber": 108,
          "pageNumber": 141,
          "lineNumber": 11,
          "wordNumber": 15,
          "location": "6:108:15",
          "audioUrl": "wbw/006_108_016.mp3",
          "charTypeName": "word",
          "codeV1": "ﯜ",
          "qpcUthmaniHafs": "لِكُلِّ",
          "textUthmani": "لِكُلِّ",
          "translation": "to every",
          "transliteration": "likulli"
        },
        {
          "chapterNumber": 6,
          "verseNumber": 108,
          "pageNumber": 141,
          "lineNumber": 11,
          "wordNumber": 16,
          "location": "6:108:16",
          "audioUrl": "wbw/006_108_017.mp3",
          "charTypeName": "word",
          "codeV1": "ﯝ",
          "qpcUthmaniHafs": "أُمَّةٍ",
          "textUthmani": "أُمَّةٍ",
          "translation": "community",
          "transliteration": "ummatin"
        },
        {
          "chapterNumber": 6,
          "verseNumber": 108,
          "pageNumber": 141,
          "lineNumber": 11,
          "wordNumber": 17,
          "location": "6:108:17",
          "audioUrl": "wbw/006_108_018.mp3",
          "charTypeName": "word",
          "codeV1": "ﯞ",
          "qpcUthmaniHafs": "عَمَلَهُمۡ",
          "textUthmani": "عَمَلَهُمْ",
          "translation": "their deed",
          "transliteration": "ʿamalahum"
        },
        {
          "chapterNumber": 6,
          "verseNumber": 108,
          "pageNumber": 141,
          "lineNumber": 11,
          "wordNumber": 18,
          "location": "6:108:18",
          "audioUrl": "wbw/006_108_019.mp3",
          "charTypeName": "word",
          "codeV1": "ﯟ",
          "qpcUthmaniHafs": "ثُمَّ",
          "textUthmani": "ثُمَّ",
          "translation": "Then",
          "transliteration": "thumma"
        },
        {
          "chapterNumber": 6,
          "verseNumber": 108,
          "pageNumber": 141,
          "lineNumber": 11,
          "wordNumber": 19,
          "location": "6:108:19",
          "audioUrl": "wbw/006_108_020.mp3",
          "charTypeName": "word",
          "codeV1": "ﯠ",
          "qpcUthmaniHafs": "إِلَىٰ",
          "textUthmani": "إِلَىٰ",
          "translation": "to",
          "transliteration": "ilā"
        },
        {
          "chapterNumber": 6,
          "verseNumber": 108,
          "pageNumber": 141,
          "lineNumber": 11,
          "wordNumber": 20,
          "location": "6:108:20",
          "audioUrl": "wbw/006_108_021.mp3",
          "charTypeName": "word",
          "codeV1": "ﯡ",
          "qpcUthmaniHafs": "رَبِّهِم",
          "textUthmani": "رَبِّهِم",
          "translation": "their Lord",
          "transliteration": "rabbihim"
        },
        {
          "chapterNumber": 6,
          "verseNumber": 108,
          "pageNumber": 141,
          "lineNumber": 11,
          "wordNumber": 21,
          "location": "6:108:21",
          "audioUrl": "wbw/006_108_022.mp3",
          "charTypeName": "word",
          "codeV1": "ﯢ",
          "qpcUthmaniHafs": "مَّرۡجِعُهُمۡ",
          "textUthmani": "مَّرْجِعُهُمْ",
          "translation": "(is) their return",
          "transliteration": "marjiʿuhum"
        },
        {
          "chapterNumber": 6,
          "verseNumber": 108,
          "pageNumber": 141,
          "lineNumber": 11,
          "wordNumber": 22,
          "location": "6:108:22",
          "audioUrl": "wbw/006_108_023.mp3",
          "charTypeName": "word",
          "codeV1": "ﯣ",
          "qpcUthmaniHafs": "فَيُنَبِّئُهُم",
          "textUthmani": "فَيُنَبِّئُهُم",
          "translation": "then He will inform them",
          "transliteration": "fayunabbi-uhum"
        },
        {
          "chapterNumber": 6,
          "verseNumber": 108,
          "pageNumber": 141,
          "lineNumber": 11,
          "wordNumber": 23,
          "location": "6:108:23",
          "audioUrl": "wbw/006_108_024.mp3",
          "charTypeName": "word",
          "codeV1": "ﯤ",
          "qpcUthmaniHafs": "بِمَا",
          "textUthmani": "بِمَا",
          "translation": "about what",
          "transliteration": "bimā"
        },
        {
          "chapterNumber": 6,
          "verseNumber": 108,
          "pageNumber": 141,
          "lineNumber": 11,
          "wordNumber": 24,
          "location": "6:108:24",
          "audioUrl": "wbw/006_108_025.mp3",
          "charTypeName": "word",
          "codeV1": "ﯥ",
          "qpcUthmaniHafs": "كَانُواْ",
          "textUthmani": "كَانُوا۟",
          "translation": "they used to",
          "transliteration": "kānū"
        },
        {
          "chapterNumber": 6,
          "verseNumber": 108,
          "pageNumber": 141,
          "lineNumber": 12,
          "wordNumber": 25,
          "location": "6:108:25",
          "audioUrl": "wbw/006_108_026.mp3",
          "charTypeName": "word",
          "codeV1": "ﯦ",
          "qpcUthmaniHafs": "يَعۡمَلُونَ",
          "textUthmani": "يَعْمَلُونَ",
          "translation": "do",
          "transliteration": "yaʿmalūna"
        },
        {
          "chapterNumber": 6,
          "verseNumber": 108,
          "pageNumber": 141,
          "lineNumber": 12,
          "wordNumber": 26,
          "location": "6:108:26",
          "audioUrl": null,
          "charTypeName": "end",
          "codeV1": "ﯧ",
          "qpcUthmaniHafs": "١٠٨",
          "textUthmani": "١٠٨",
          "translation": "(108)",
          "transliteration": null
        }
      ]
    },
    {
      "chapterNumber": 6,
      "verseNumber": 109,
      "verseKey": "6:109",
      "pageNumber": 141,
      "isManzil": false,
      "manzilNumber": 2,
      "isJuz": false,
      "juzNumber": 7,
      "isHizb": false,
      "hizbNumber": 14,
      "isRubElHizb": false,
      "rubElHizbNumber": 56,
      "isRuku": false,
      "rukuNumber": 114,
      "isSajdah": false,
      "sajdahNumber": null,
      "textUthmani": "وَأَقْسَمُوا۟ بِٱللَّهِ جَهْدَ أَيْمَـٰنِهِمْ لَئِن جَآءَتْهُمْ ءَايَةٌ لَّيُؤْمِنُنَّ بِهَا ۚ قُلْ إِنَّمَا ٱلْـَٔايَـٰتُ عِندَ ٱللَّهِ ۖ وَمَا يُشْعِرُكُمْ أَنَّهَآ إِذَا جَآءَتْ لَا يُؤْمِنُونَ",
      "wordByWord": "وَأَقْسَمُوا۟ [And they swear] بِٱللَّهِ [by Allah] جَهْدَ [strongest] أَيْمَـٰنِهِمْ [(of) their oaths] لَئِن [that if] جَآءَتْهُمْ [came to them] ءَايَةٌۭ [a sign] لَّيُؤْمِنُنَّ [they would surely believe] بِهَا ۚ [in it] قُلْ [Say] إِنَّمَا [Only] ٱلْـَٔايَـٰتُ [the signs] عِندَ [(are) with] ٱللَّهِ ۖ [Allah] وَمَا [And what] يُشْعِرُكُمْ [will make you perceive] أَنَّهَآ [that [it]] إِذَا [when] جَآءَتْ [it comes] لَا [not] يُؤْمِنُونَ [they will believe]",
      "transliteration": "Waaqsamoo billahi jahda aymanihimla-in jaat-hum ayatun layu/minunna biha qulinnama al-ayatu AAinda Allahi wamayushAAirukum annaha itha jaat layu/minoon",
      "reciterTimestamps": {
        "Mishari Rashid al-`Afasy": {
          "timestampFrom": 2649360,
          "timestampTo": 2681700
        }
      },
      "words": [
        {
          "chapterNumber": 6,
          "verseNumber": 109,
          "pageNumber": 141,
          "lineNumber": 12,
          "wordNumber": 1,
          "location": "6:109:1",
          "audioUrl": "wbw/006_109_001.mp3",
          "charTypeName": "word",
          "codeV1": "ﯨ",
          "qpcUthmaniHafs": "وَأَقۡسَمُواْ",
          "textUthmani": "وَأَقْسَمُوا۟",
          "translation": "And they swear",
          "transliteration": "wa-aqsamū"
        },
        {
          "chapterNumber": 6,
          "verseNumber": 109,
          "pageNumber": 141,
          "lineNumber": 12,
          "wordNumber": 2,
          "location": "6:109:2",
          "audioUrl": "wbw/006_109_002.mp3",
          "charTypeName": "word",
          "codeV1": "ﯩ",
          "qpcUthmaniHafs": "بِٱللَّهِ",
          "textUthmani": "بِٱللَّهِ",
          "translation": "by Allah",
          "transliteration": "bil-lahi"
        },
        {
          "chapterNumber": 6,
          "verseNumber": 109,
          "pageNumber": 141,
          "lineNumber": 12,
          "wordNumber": 3,
          "location": "6:109:3",
          "audioUrl": "wbw/006_109_003.mp3",
          "charTypeName": "word",
          "codeV1": "ﯪ",
          "qpcUthmaniHafs": "جَهۡدَ",
          "textUthmani": "جَهْدَ",
          "translation": "strongest",
          "transliteration": "jahda"
        },
        {
          "chapterNumber": 6,
          "verseNumber": 109,
          "pageNumber": 141,
          "lineNumber": 12,
          "wordNumber": 4,
          "location": "6:109:4",
          "audioUrl": "wbw/006_109_004.mp3",
          "charTypeName": "word",
          "codeV1": "ﯫ",
          "qpcUthmaniHafs": "أَيۡمَٰنِهِمۡ",
          "textUthmani": "أَيْمَـٰنِهِمْ",
          "translation": "(of) their oaths",
          "transliteration": "aymānihim"
        },
        {
          "chapterNumber": 6,
          "verseNumber": 109,
          "pageNumber": 141,
          "lineNumber": 12,
          "wordNumber": 5,
          "location": "6:109:5",
          "audioUrl": "wbw/006_109_005.mp3",
          "charTypeName": "word",
          "codeV1": "ﯬ",
          "qpcUthmaniHafs": "لَئِن",
          "textUthmani": "لَئِن",
          "translation": "that if",
          "transliteration": "la-in"
        },
        {
          "chapterNumber": 6,
          "verseNumber": 109,
          "pageNumber": 141,
          "lineNumber": 12,
          "wordNumber": 6,
          "location": "6:109:6",
          "audioUrl": "wbw/006_109_006.mp3",
          "charTypeName": "word",
          "codeV1": "ﯭ",
          "qpcUthmaniHafs": "جَآءَتۡهُمۡ",
          "textUthmani": "جَآءَتْهُمْ",
          "translation": "came to them",
          "transliteration": "jāathum"
        },
        {
          "chapterNumber": 6,
          "verseNumber": 109,
          "pageNumber": 141,
          "lineNumber": 12,
          "wordNumber": 7,
          "location": "6:109:7",
          "audioUrl": "wbw/006_109_007.mp3",
          "charTypeName": "word",
          "codeV1": "ﯮ",
          "qpcUthmaniHafs": "ءَايَةٞ",
          "textUthmani": "ءَايَةٌۭ",
          "translation": "a sign",
          "transliteration": "āyatun"
        },
        {
          "chapterNumber": 6,
          "verseNumber": 109,
          "pageNumber": 141,
          "lineNumber": 13,
          "wordNumber": 8,
          "location": "6:109:8",
          "audioUrl": "wbw/006_109_008.mp3",
          "charTypeName": "word",
          "codeV1": "ﯯ",
          "qpcUthmaniHafs": "لَّيُؤۡمِنُنَّ",
          "textUthmani": "لَّيُؤْمِنُنَّ",
          "translation": "they would surely believe",
          "transliteration": "layu'minunna"
        },
        {
          "chapterNumber": 6,
          "verseNumber": 109,
          "pageNumber": 141,
          "lineNumber": 13,
          "wordNumber": 9,
          "location": "6:109:9",
          "audioUrl": "wbw/006_109_009.mp3",
          "charTypeName": "word",
          "codeV1": "ﯰﯱ",
          "qpcUthmaniHafs": "بِهَاۚ",
          "textUthmani": "بِهَا ۚ",
          "translation": "in it",
          "transliteration": "bihā"
        },
        {
          "chapterNumber": 6,
          "verseNumber": 109,
          "pageNumber": 141,
          "lineNumber": 13,
          "wordNumber": 10,
          "location": "6:109:10",
          "audioUrl": "wbw/006_109_011.mp3",
          "charTypeName": "word",
          "codeV1": "ﯲ",
          "qpcUthmaniHafs": "قُلۡ",
          "textUthmani": "قُلْ",
          "translation": "Say",
          "transliteration": "qul"
        },
        {
          "chapterNumber": 6,
          "verseNumber": 109,
          "pageNumber": 141,
          "lineNumber": 13,
          "wordNumber": 11,
          "location": "6:109:11",
          "audioUrl": "wbw/006_109_012.mp3",
          "charTypeName": "word",
          "codeV1": "ﯳ",
          "qpcUthmaniHafs": "إِنَّمَا",
          "textUthmani": "إِنَّمَا",
          "translation": "Only",
          "transliteration": "innamā"
        },
        {
          "chapterNumber": 6,
          "verseNumber": 109,
          "pageNumber": 141,
          "lineNumber": 13,
          "wordNumber": 12,
          "location": "6:109:12",
          "audioUrl": "wbw/006_109_013.mp3",
          "charTypeName": "word",
          "codeV1": "ﯴ",
          "qpcUthmaniHafs": "ٱلۡأٓيَٰتُ",
          "textUthmani": "ٱلْـَٔايَـٰتُ",
          "translation": "the signs",
          "transliteration": "l-āyātu"
        },
        {
          "chapterNumber": 6,
          "verseNumber": 109,
          "pageNumber": 141,
          "lineNumber": 13,
          "wordNumber": 13,
          "location": "6:109:13",
          "audioUrl": "wbw/006_109_014.mp3",
          "charTypeName": "word",
          "codeV1": "ﯵ",
          "qpcUthmaniHafs": "عِندَ",
          "textUthmani": "عِندَ",
          "translation": "(are) with",
          "transliteration": "ʿinda"
        },
        {
          "chapterNumber": 6,
          "verseNumber": 109,
          "pageNumber": 141,
          "lineNumber": 13,
          "wordNumber": 14,
          "location": "6:109:14",
          "audioUrl": "wbw/006_109_015.mp3",
          "charTypeName": "word",
          "codeV1": "ﯶﯷ",
          "qpcUthmaniHafs": "ٱللَّهِۖ",
          "textUthmani": "ٱللَّهِ ۖ",
          "translation": "Allah",
          "transliteration": "l-lahi"
        },
        {
          "chapterNumber": 6,
          "verseNumber": 109,
          "pageNumber": 141,
          "lineNumber": 13,
          "wordNumber": 15,
          "location": "6:109:15",
          "audioUrl": "wbw/006_109_017.mp3",
          "charTypeName": "word",
          "codeV1": "ﯸ",
          "qpcUthmaniHafs": "وَمَا",
          "textUthmani": "وَمَا",
          "translation": "And what",
          "transliteration": "wamā"
        },
        {
          "chapterNumber": 6,
          "verseNumber": 109,
          "pageNumber": 141,
          "lineNumber": 13,
          "wordNumber": 16,
          "location": "6:109:16",
          "audioUrl": "wbw/006_109_018.mp3",
          "charTypeName": "word",
          "codeV1": "ﯹ",
          "qpcUthmaniHafs": "يُشۡعِرُكُمۡ",
          "textUthmani": "يُشْعِرُكُمْ",
          "translation": "will make you perceive",
          "transliteration": "yush'ʿirukum"
        },
        {
          "chapterNumber": 6,
          "verseNumber": 109,
          "pageNumber": 141,
          "lineNumber": 13,
          "wordNumber": 17,
          "location": "6:109:17",
          "audioUrl": "wbw/006_109_019.mp3",
          "charTypeName": "word",
          "codeV1": "ﯺ",
          "qpcUthmaniHafs": "أَنَّهَآ",
          "textUthmani": "أَنَّهَآ",
          "translation": "that [it]",
          "transliteration": "annahā"
        },
        {
          "chapterNumber": 6,
          "verseNumber": 109,
          "pageNumber": 141,
          "lineNumber": 13,
          "wordNumber": 18,
          "location": "6:109:18",
          "audioUrl": "wbw/006_109_020.mp3",
          "charTypeName": "word",
          "codeV1": "ﯻ",
          "qpcUthmaniHafs": "إِذَا",
          "textUthmani": "إِذَا",
          "translation": "when",
          "transliteration": "idhā"
        },
        {
          "chapterNumber": 6,
          "verseNumber": 109,
          "pageNumber": 141,
          "lineNumber": 14,
          "wordNumber": 19,
          "location": "6:109:19",
          "audioUrl": "wbw/006_109_021.mp3",
          "charTypeName": "word",
          "codeV1": "ﯼ",
          "qpcUthmaniHafs": "جَآءَتۡ",
          "textUthmani": "جَآءَتْ",
          "translation": "it comes",
          "transliteration": "jāat"
        },
        {
          "chapterNumber": 6,
          "verseNumber": 109,
          "pageNumber": 141,
          "lineNumber": 14,
          "wordNumber": 20,
          "location": "6:109:20",
          "audioUrl": "wbw/006_109_022.mp3",
          "charTypeName": "word",
          "codeV1": "ﯽ",
          "qpcUthmaniHafs": "لَا",
          "textUthmani": "لَا",
          "translation": "not",
          "transliteration": "lā"
        },
        {
          "chapterNumber": 6,
          "verseNumber": 109,
          "pageNumber": 141,
          "lineNumber": 14,
          "wordNumber": 21,
          "location": "6:109:21",
          "audioUrl": "wbw/006_109_023.mp3",
          "charTypeName": "word",
          "codeV1": "ﯾ",
          "qpcUthmaniHafs": "يُؤۡمِنُونَ",
          "textUthmani": "يُؤْمِنُونَ",
          "translation": "they will believe",
          "transliteration": "yu'minūna"
        },
        {
          "chapterNumber": 6,
          "verseNumber": 109,
          "pageNumber": 141,
          "lineNumber": 14,
          "wordNumber": 22,
          "location": "6:109:22",
          "audioUrl": null,
          "charTypeName": "end",
          "codeV1": "ﯿ",
          "qpcUthmaniHafs": "١٠٩",
          "textUthmani": "١٠٩",
          "translation": "(109)",
          "transliteration": null
        }
      ]
    },
    {
      "chapterNumber": 6,
      "verseNumber": 110,
      "verseKey": "6:110",
      "pageNumber": 141,
      "manzilNumber": 2,
      "juzNumber": 7,
      "hizbNumber": 14,
      "rubElHizbNumber": 56,
      "rukuNumber": 114,
      "isSajdah": false,
      "sajdahNumber": null,
      "textUthmani": "وَنُقَلِّبُ أَفْـِٔدَتَهُمْ وَأَبْصَـٰرَهُمْ كَمَا لَمْ يُؤْمِنُوا۟ بِهِۦٓ أَوَّلَ مَرَّةٍ وَنَذَرُهُمْ فِى طُغْيَـٰنِهِمْ يَعْمَهُونَ",
      "wordByWord": "وَنُقَلِّبُ [And We will turn] أَفْـِٔدَتَهُمْ [their hearts] وَأَبْصَـٰرَهُمْ [and their sights] كَمَا [(just) as] لَمْ [not] يُؤْمِنُوا۟ [they believe] بِهِۦٓ [in it] أَوَّلَ [(the) first] مَرَّةٍۢ [time] وَنَذَرُهُمْ [And We will leave them] فِى [in] طُغْيَـٰنِهِمْ [their transgression] يَعْمَهُونَ [wandering blindly]",
      "transliteration": "Wanuqallibu af-idatahum waabsarahumkama lam yu/minoo bihi awwala marratin wanatharuhumfee tughyanihim yaAAmahoon",
      "reciterTimestamps": {
        "Mishari Rashid al-`Afasy": {
          "timestampFrom": 2681700,
          "timestampTo": 2700900
        },
        "Shaykh Samir al-Nass": {
          "timestampFrom": 0,
          "timestampTo": 2581
        }
      },
      "words": [
        {
          "chapterNumber": 6,
          "verseNumber": 110,
          "pageNumber": 141,
          "lineNumber": 14,
          "wordNumber": 1,
          "location": "6:110:1",
          "audioUrl": "wbw/006_110_001.mp3",
          "charTypeName": "word",
          "codeV1": "ﰀ",
          "qpcUthmaniHafs": "وَنُقَلِّبُ",
          "textUthmani": "وَنُقَلِّبُ",
          "translation": "And We will turn",
          "transliteration": "wanuqallibu"
        },
        {
          "chapterNumber": 6,
          "verseNumber": 110,
          "pageNumber": 141,
          "lineNumber": 14,
          "wordNumber": 2,
          "location": "6:110:2",
          "audioUrl": "wbw/006_110_002.mp3",
          "charTypeName": "word",
          "codeV1": "ﰁ",
          "qpcUthmaniHafs": "أَفۡـِٔدَتَهُمۡ",
          "textUthmani": "أَفْـِٔدَتَهُمْ",
          "translation": "their hearts",
          "transliteration": "afidatahum"
        },
        {
          "chapterNumber": 6,
          "verseNumber": 110,
          "pageNumber": 141,
          "lineNumber": 14,
          "wordNumber": 3,
          "location": "6:110:3",
          "audioUrl": "wbw/006_110_003.mp3",
          "charTypeName": "word",
          "codeV1": "ﰂ",
          "qpcUthmaniHafs": "وَأَبۡصَٰرَهُمۡ",
          "textUthmani": "وَأَبْصَـٰرَهُمْ",
          "translation": "and their sights",
          "transliteration": "wa-abṣārahum"
        },
        {
          "chapterNumber": 6,
          "verseNumber": 110,
          "pageNumber": 141,
          "lineNumber": 14,
          "wordNumber": 4,
          "location": "6:110:4",
          "audioUrl": "wbw/006_110_004.mp3",
          "charTypeName": "word",
          "codeV1": "ﰃ",
          "qpcUthmaniHafs": "كَمَا",
          "textUthmani": "كَمَا",
          "translation": "(just) as",
          "transliteration": "kamā"
        },
        {
          "chapterNumber": 6,
          "verseNumber": 110,
          "pageNumber": 141,
          "lineNumber": 14,
          "wordNumber": 5,
          "location": "6:110:5",
          "audioUrl": "wbw/006_110_005.mp3",
          "charTypeName": "word",
          "codeV1": "ﰄ",
          "qpcUthmaniHafs": "لَمۡ",
          "textUthmani": "لَمْ",
          "translation": "not",
          "transliteration": "lam"
        },
        {
          "chapterNumber": 6,
          "verseNumber": 110,
          "pageNumber": 141,
          "lineNumber": 15,
          "wordNumber": 6,
          "location": "6:110:6",
          "audioUrl": "wbw/006_110_006.mp3",
          "charTypeName": "word",
          "codeV1": "ﰅ",
          "qpcUthmaniHafs": "يُؤۡمِنُواْ",
          "textUthmani": "يُؤْمِنُوا۟",
          "translation": "they believe",
          "transliteration": "yu'minū"
        },
        {
          "chapterNumber": 6,
          "verseNumber": 110,
          "pageNumber": 141,
          "lineNumber": 15,
          "wordNumber": 7,
          "location": "6:110:7",
          "audioUrl": "wbw/006_110_007.mp3",
          "charTypeName": "word",
          "codeV1": "ﰆ",
          "qpcUthmaniHafs": "بِهِۦٓ",
          "textUthmani": "بِهِۦٓ",
          "translation": "in it",
          "transliteration": "bihi"
        },
        {
          "chapterNumber": 6,
          "verseNumber": 110,
          "pageNumber": 141,
          "lineNumber": 15,
          "wordNumber": 8,
          "location": "6:110:8",
          "audioUrl": "wbw/006_110_008.mp3",
          "charTypeName": "word",
          "codeV1": "ﰇ",
          "qpcUthmaniHafs": "أَوَّلَ",
          "textUthmani": "أَوَّلَ",
          "translation": "(the) first",
          "transliteration": "awwala"
        },
        {
          "chapterNumber": 6,
          "verseNumber": 110,
          "pageNumber": 141,
          "lineNumber": 15,
          "wordNumber": 9,
          "location": "6:110:9",
          "audioUrl": "wbw/006_110_009.mp3",
          "charTypeName": "word",
          "codeV1": "ﰈ",
          "qpcUthmaniHafs": "مَرَّةٖ",
          "textUthmani": "مَرَّةٍۢ",
          "translation": "time",
          "transliteration": "marratin"
        },
        {
          "chapterNumber": 6,
          "verseNumber": 110,
          "pageNumber": 141,
          "lineNumber": 15,
          "wordNumber": 10,
          "location": "6:110:10",
          "audioUrl": "wbw/006_110_010.mp3",
          "charTypeName": "word",
          "codeV1": "ﰉ",
          "qpcUthmaniHafs": "وَنَذَرُهُمۡ",
          "textUthmani": "وَنَذَرُهُمْ",
          "translation": "And We will leave them",
          "transliteration": "wanadharuhum"
        },
        {
          "chapterNumber": 6,
          "verseNumber": 110,
          "pageNumber": 141,
          "lineNumber": 15,
          "wordNumber": 11,
          "location": "6:110:11",
          "audioUrl": "wbw/006_110_011.mp3",
          "charTypeName": "word",
          "codeV1": "ﰊ",
          "qpcUthmaniHafs": "فِي",
          "textUthmani": "فِى",
          "translation": "in",
          "transliteration": "fī"
        },
        {
          "chapterNumber": 6,
          "verseNumber": 110,
          "pageNumber": 141,
          "lineNumber": 15,
          "wordNumber": 12,
          "location": "6:110:12",
          "audioUrl": "wbw/006_110_012.mp3",
          "charTypeName": "word",
          "codeV1": "ﰋ",
          "qpcUthmaniHafs": "طُغۡيَٰنِهِمۡ",
          "textUthmani": "طُغْيَـٰنِهِمْ",
          "translation": "their transgression",
          "transliteration": "ṭugh'yānihim"
        },
        {
          "chapterNumber": 6,
          "verseNumber": 110,
          "pageNumber": 141,
          "lineNumber": 15,
          "wordNumber": 13,
          "location": "6:110:13",
          "audioUrl": "wbw/006_110_013.mp3",
          "charTypeName": "word",
          "codeV1": "ﰌ",
          "qpcUthmaniHafs": "يَعۡمَهُونَ",
          "textUthmani": "يَعْمَهُونَ",
          "translation": "wandering blindly",
          "transliteration": "yaʿmahūna"
        },
        {
          "chapterNumber": 6,
          "verseNumber": 110,
          "pageNumber": 141,
          "lineNumber": 15,
          "wordNumber": 14,
          "location": "6:110:14",
          "audioUrl": null,
          "charTypeName": "end",
          "codeV1": "ﰍ",
          "qpcUthmaniHafs": "١١٠",
          "textUthmani": "١١٠",
          "translation": "(110)",
          "transliteration": null
        }
      ]
    }
  ]
}